container_ci_suite/__init__.py
container_ci_suite/constants.py
container_ci_suite/container_lib.py
container_ci_suite/dockerfile_processor.py
container_ci_suite/example_usage.py
container_ci_suite/exceptions.py
container_ci_suite/git.py
container_ci_suite/helm.py
container_ci_suite/imagestreams.py
container_ci_suite/logger.py
container_ci_suite/openshift.py
container_ci_suite/s2i_example.py
container_ci_suite/test_lib.py
container_ci_suite/utils.py
container_ci_suite/engines/__init__.py
container_ci_suite/engines/container.py
container_ci_suite/engines/database.py
container_ci_suite/engines/imagestreams.py
container_ci_suite/engines/openshift.py
container_ci_suite/engines/podman_wrapper.py
container_ci_suite/engines/s2i_container.py
container_ci_suite-0.11.2.dist-info/licenses/LICENSE
container_ci_suite-0.11.2.dist-info/METADATA
container_ci_suite-0.11.2.dist-info/WHEEL
container_ci_suite-0.11.2.dist-info/top_level.txt
container_ci_suite-0.11.2.dist-info/RECORD
