Metadata-Version: 2.4
Name: container-ci-suite
Version: 0.11.2
Summary: A python3 container CI tool for testing images.
Home-page: https://github.com/sclorg/container-ci-suite
Author: Petr Hracek
Author-email: phracek@redhat.com
License: MIT
Keywords: tool,containers,images,tests
Classifier: Development Status :: 4 - Beta
Classifier: Environment :: Console
Classifier: Intended Audience :: Developers
Classifier: License :: OSI Approved :: MIT License
Classifier: Operating System :: POSIX :: Linux
Classifier: Programming Language :: Python
Classifier: Topic :: Software Development
License-File: LICENSE
Requires-Dist: packaging
Requires-Dist: pytest
Requires-Dist: flexmock
Requires-Dist: GitPython
Requires-Dist: requests
Requires-Dist: PyYAML
Dynamic: author
Dynamic: author-email
Dynamic: classifier
Dynamic: description
Dynamic: description-content-type
Dynamic: home-page
Dynamic: keywords
Dynamic: license
Dynamic: license-file
Dynamic: requires-dist
Dynamic: summary
